{
    "series": ["Muži", "Ženy", "Nezaměstnanost"],
    "data": [{
      "x": "1989",
      "y": [68.1, 75.4, 0]
    }, {
      "x": "1990",
      "y": [67.6, 75.4, 0.66]
    }, {
      "x": "1991",
      "y": [68.2, 75.7, 4.13]
    }, {
      "x": "1992",
      "y": [68.5, 76.1, 2.57]
    }, {
      "x": "1993",
      "y": [69.3, 76.4, 3.52]
    }, {
      "x": "1994",
      "y": [69.5, 76.6, 3.19]
    }, {
      "x": "1995",
      "y": [69.7, 76.6, 2.93]
    }, {
      "x": "1996",
      "y": [70.4, 77.3, 3.52]
    }, {
      "x": "1997",
      "y": [70.5, 77.5, 5.23]
    }, {
      "x": "1998",
      "y": [71.1, 78.1, 7.48]
    }, {
      "x": "1999",
      "y": [71.4, 78.1, 9.37]
    }, {
      "x": "2000",
      "y": [71.6, 78.3, 8.78]
    }, {
      "x": "2001",
      "y": [72.1, 78.4, 8.90]
    }, {
      "x": "2002",
      "y": [72.1, 78.5, 9.81]
    }, {
      "x": "2003",
      "y": [72.0, 78.5, 10.31]
    }, {
      "x": "2004",
      "y": [72.5, 79.0, 10.33]
    }, {
      "x": "2005",
      "y": [72.9, 79.1, 9.47]
    }, {
      "x": "2006",
      "y": [73.4, 79.7, 8.88]
    }, {
      "x": "2007",
      "y": [73.7, 79.9, 7.67]
    }, {
      "x": "2008",
      "y": [74.0, 80.1, 5.98]
    }, {
      "x": "2009",
      "y": [74.2, 80.1, 5.96]
    }, {
      "x": "2010",
      "y": [74.4, 80.6, 9.24]
    }, {
      "x": "2011",
      "y": [74.7, 80.7, 9.57]
    }, {
      "x": "2012",
      "y": [75.0, 80.9, 8.62]
    }, {
      "x": "2013",
      "y": [75.4, 81.3, 9.36]
    }]
  }
